anonymouus/__init__.py
anonymouus/anonymouus.py
anonymoUUs-0.0.8.dist-info/METADATA
anonymoUUs-0.0.8.dist-info/WHEEL
anonymoUUs-0.0.8.dist-info/top_level.txt
anonymoUUs-0.0.8.dist-info/RECORD
