Metadata-Version: 2.1
Name: anonymoUUs
Version: 0.0.8
Summary: A tool to substitue patterns/names in a file tree
Home-page: https://github.com/UtrechtUniversity/anonymouus
Author: C.S. Kaandorp
Author-email: c.s.kaandorp@uu.nl
License: MIT
Platform: UNKNOWN
Requires-Python: >=3.6
